MANIFEST.in
README.md
hgmeans.cpp
hgmeans.pyx
setup.cfg
setup.py
hgmeans/GeneticOperations.cpp
hgmeans/GeneticOperations.h
hgmeans/HGMeans.cpp
hgmeans/HGMeans.h
hgmeans/MathUtils.cpp
hgmeans/MathUtils.h
hgmeans/PbData.h
hgmeans/Solution.cpp
hgmeans/Solution.h
hgmeans.egg-info/PKG-INFO
hgmeans.egg-info/SOURCES.txt
hgmeans.egg-info/dependency_links.txt
hgmeans.egg-info/top_level.txt
hgmeans/dlib-master/dlib/algs.h
hgmeans/dlib-master/dlib/any.h
hgmeans/dlib-master/dlib/array.h
hgmeans/dlib-master/dlib/array2d.h
hgmeans/dlib-master/dlib/assert.h
hgmeans/dlib-master/dlib/base64.h
hgmeans/dlib-master/dlib/bayes_utils.h
hgmeans/dlib-master/dlib/bigint.h
hgmeans/dlib-master/dlib/binary_search_tree.h
hgmeans/dlib-master/dlib/bit_stream.h
hgmeans/dlib-master/dlib/bound_function_pointer.h
hgmeans/dlib-master/dlib/bridge.h
hgmeans/dlib-master/dlib/bsp.h
hgmeans/dlib-master/dlib/byte_orderer.h
hgmeans/dlib-master/dlib/clustering.h
hgmeans/dlib-master/dlib/cmd_line_parser.h
hgmeans/dlib-master/dlib/compress_stream.h
hgmeans/dlib-master/dlib/conditioning_class.h
hgmeans/dlib-master/dlib/config.h
hgmeans/dlib-master/dlib/config_reader.h
hgmeans/dlib-master/dlib/console_progress_indicator.h
hgmeans/dlib-master/dlib/control.h
hgmeans/dlib-master/dlib/cpp_pretty_printer.h
hgmeans/dlib-master/dlib/cpp_tokenizer.h
hgmeans/dlib-master/dlib/crc32.h
hgmeans/dlib-master/dlib/data_io.h
hgmeans/dlib-master/dlib/dir_nav.h
hgmeans/dlib-master/dlib/directed_graph.h
hgmeans/dlib-master/dlib/disjoint_subsets.h
hgmeans/dlib-master/dlib/enable_if.h
hgmeans/dlib-master/dlib/entropy_decoder.h
hgmeans/dlib-master/dlib/entropy_decoder_model.h
hgmeans/dlib-master/dlib/entropy_encoder.h
hgmeans/dlib-master/dlib/entropy_encoder_model.h
hgmeans/dlib-master/dlib/error.h
hgmeans/dlib-master/dlib/filtering.h
hgmeans/dlib-master/dlib/float_details.h
hgmeans/dlib-master/dlib/geometry.h
hgmeans/dlib-master/dlib/graph.h
hgmeans/dlib-master/dlib/graph_cuts.h
hgmeans/dlib-master/dlib/graph_utils.h
hgmeans/dlib-master/dlib/graph_utils_threaded.h
hgmeans/dlib-master/dlib/gui_core.h
hgmeans/dlib-master/dlib/gui_widgets.h
