Metadata-Version: 1.1
Name: hgmeans
Version: 3.0
Summary: HG-means clustering for minimum sum-of-squares formulation
Home-page: https://github.com/danielgribel/hg-means
Author: Daniel Gribel
Author-email: dgribel@inf.puc-rio.br
License: UNKNOWN
Keywords: clustering optimization
Platform: UNKNOWN
Classifier: License :: OSI Approved :: GNU General Public License v3 or later (GPLv3+)
Classifier: Programming Language :: Python
